hvthu_bypass_captcha_tiktok/__init__.py
hvthu_bypass_captcha_tiktok/module.py
hvthu_bypass_captcha_tiktok-0.1.0.dist-info/METADATA
hvthu_bypass_captcha_tiktok-0.1.0.dist-info/WHEEL
hvthu_bypass_captcha_tiktok-0.1.0.dist-info/top_level.txt
hvthu_bypass_captcha_tiktok-0.1.0.dist-info/RECORD
