Metadata-Version: 2.1
Name: hvthu-bypass-captcha-tiktok
Version: 0.1.0
Summary: Mô tả ngắn về package
Home-page: https://github.com/yourusername/my_package
Author: Tên của bạn
Author-email: email@example.com
Classifier: Programming Language :: Python :: 3
Classifier: License :: OSI Approved :: MIT License
Classifier: Operating System :: OS Independent
Requires-Python: >=3.6
